ycmd/ClassData.py
ycmd/__init__.py
ycmd/__main__.py
ycmd/ycmd.py
ycmd-0.0.3.dist-info/METADATA
ycmd-0.0.3.dist-info/WHEEL
ycmd-0.0.3.dist-info/entry_points.txt
ycmd-0.0.3.dist-info/top_level.txt
ycmd-0.0.3.dist-info/RECORD
