Metadata-Version: 2.1
Name: ycmd
Version: 0.0.3
Summary: ycmd code runner
Home-page: https://github.com/ysmservice/ycmd
Author: ysmreg
Author-email: ysmreg1@gmail.com
License: UNKNOWN
Platform: UNKNOWN
Classifier: Programming Language :: Python :: 3
Classifier: License :: OSI Approved :: MIT License
Classifier: Operating System :: OS Independent
Requires-Python: >=3.7
